baserush/__init__.py
baserush/_utils.py
baserush/optimize.py
baserush/preprocess.py
baserush/summary.py
baserush-0.0.1.dist-info/licenses/LICENSE.txt
baserush-0.0.1.dist-info/METADATA
baserush-0.0.1.dist-info/WHEEL
baserush-0.0.1.dist-info/top_level.txt
baserush-0.0.1.dist-info/RECORD
