Metadata-Version: 2.4
Name: baserush
Version: 0.0.1
Summary: An easy-to-use regression pipeline to preprocess, analyze, and optimize models.
Author-email: Chase Kusterer <chase.kusterer24@gmail.com>
License: MIT
Project-URL: Homepage, https://github.com/chase-kusterer/basemodeler
Project-URL: Issues, https://github.com/chase-kusterer/basemodeler/issues
Keywords: regression,scikit-learn,machine-learning,preprocessing,model-selection,model-optimization,linear-modeling,nonparametric-modeling,knn
Classifier: Development Status :: 3 - Alpha
Classifier: Intended Audience :: Science/Research
Classifier: License :: OSI Approved :: MIT License
Classifier: Programming Language :: Python :: 3
Classifier: Programming Language :: Python :: 3 :: Only
Classifier: Programming Language :: Python :: 3.9
Classifier: Topic :: Scientific/Engineering :: Artificial Intelligence
Classifier: Topic :: Scientific/Engineering :: Information Analysis
Classifier: Operating System :: OS Independent
Requires-Python: >=3.9
License-File: LICENSE.txt
Requires-Dist: numpy
Requires-Dist: pandas
Requires-Dist: scikit-learn
Requires-Dist: statsmodels
Dynamic: license-file
